<?xml version="1.0" encoding="utf-8" ?>
<dwsync>
<file name="kamy.JPG" server="93.88.240.147." local="130617724780000000" remote="130789810800000000" Dst="2" />
<file name="admin.JPG" server="93.88.240.147." local="130763309276610258" remote="130789810800000000" Dst="2" />
<file name="admin2.JPG" server="93.88.240.147." local="130763309276610258" remote="130789810800000000" Dst="2" />
<file name="no_user.png" server="93.88.240.147." local="130763537206982440" remote="130789810800000000" Dst="2" />
<file name="kamy.JPG" server="93.88.240.147" local="130617724780000000" remote="130884896400000000" Dst="2" />
<file name="admin.JPG" server="93.88.240.147" local="130763309276610258" remote="130884896400000000" Dst="2" />
<file name="admin2.JPG" server="93.88.240.147" local="130763309276610258" remote="130884896400000000" Dst="2" />
<file name="no_user.png" server="93.88.240.147" local="130763537206982440" remote="130884896400000000" Dst="2" />
<file name="no_user.jpg" server="93.88.240.147" local="130804773177456623" remote="130884896400000000" Dst="2" />
</dwsync>